./.dockerignore
./.gitignore
./Dockerfile
./PKG-INFO
./README.md
./main.py
./pyproject.toml
./uv.lock
./api/__init__.py
./api/auth.py
./api/download.py
./api/search.py
sketchfab_mcp_fastmcp-0.1.3.dist-info/METADATA
sketchfab_mcp_fastmcp-0.1.3.dist-info/WHEEL
sketchfab_mcp_fastmcp-0.1.3.dist-info/entry_points.txt
sketchfab_mcp_fastmcp-0.1.3.dist-info/RECORD
