Metadata-Version: 2.4
Name: sketchfab-mcp-fastmcp
Version: 0.1.3
Summary: A microservice for interacting with the Sketchfab API using MCP (Model Control Protocol).
Project-URL: Homepage, https://github.com/fastmcp-me/sketchfab_mcp#readme
Project-URL: Repository, https://github.com/fastmcp-me/sketchfab_mcp.git
Project-URL: Issues, https://github.com/fastmcp-me/sketchfab_mcp/issues
Author-email: Eduardo del Palacio Lirola <eduardodelpalaciolirola@gmail.com>
Requires-Python: >=3.13
Requires-Dist: mcp[cli]>=1.3.0
Requires-Dist: requests>=2.32.3
